helium_cylinder/__init__.py
helium_cylinder/decorators.py
helium_cylinder-0.1.1.dist-info/LICENSE
helium_cylinder-0.1.1.dist-info/METADATA
helium_cylinder-0.1.1.dist-info/WHEEL
helium_cylinder-0.1.1.dist-info/top_level.txt
helium_cylinder-0.1.1.dist-info/RECORD
